yacf/__init__.py
yacf/configuration.py
yacf/utils.py
yacf-1.1.1.dist-info/LICENSE
yacf-1.1.1.dist-info/METADATA
yacf-1.1.1.dist-info/WHEEL
yacf-1.1.1.dist-info/top_level.txt
yacf-1.1.1.dist-info/RECORD
