Metadata-Version: 2.1
Name: yacf
Version: 1.1.1
Summary: Yet another configuration framework - Lightweight, easy to use.
Home-page: https://github.com/resingm/yacf
Author: Max Resing
Author-email: max.resing@protonmail.com
Maintainer: Max Resing
Maintainer-email: max.resing@protonmail.com
License: MIT
Project-URL: Source, https://github.com/resingm/yacf
Project-URL: Tracker, https://github.com/resingm/yacf/issues
Keywords: configuration config toml json
Platform: UNKNOWN
Classifier: Development Status :: 5 - Production/Stable
Classifier: Intended Audience :: Developers
Classifier: License :: OSI Approved :: MIT License
Classifier: Programming Language :: Python :: 3.7
Requires-Python: >=3.6
License-File: LICENSE
Requires-Dist: toml
